odoo/addons/payroll_rule_time_parameter/README.rst
odoo/addons/payroll_rule_time_parameter/__init__.py
odoo/addons/payroll_rule_time_parameter/__manifest__.py
odoo/addons/payroll_rule_time_parameter/hooks.py
odoo/addons/payroll_rule_time_parameter/i18n/payroll_rule_time_parameter.pot
odoo/addons/payroll_rule_time_parameter/models/__init__.py
odoo/addons/payroll_rule_time_parameter/models/hr_payslip.py
odoo/addons/payroll_rule_time_parameter/readme/CONTRIBUTORS.rst
odoo/addons/payroll_rule_time_parameter/readme/DESCRIPTION.rst
odoo/addons/payroll_rule_time_parameter/security/ir.model.access.csv
odoo/addons/payroll_rule_time_parameter/static/description/icon.png
odoo/addons/payroll_rule_time_parameter/static/description/index.html
odoo/addons/payroll_rule_time_parameter/tests/__init__.py
odoo/addons/payroll_rule_time_parameter/tests/test_time_parameter.py
odoo/addons/payroll_rule_time_parameter/views/base_time_parameter_views.xml
odoo14_addon_payroll_rule_time_parameter-14.0.2.0.2.dist-info/METADATA
odoo14_addon_payroll_rule_time_parameter-14.0.2.0.2.dist-info/WHEEL
odoo14_addon_payroll_rule_time_parameter-14.0.2.0.2.dist-info/top_level.txt
odoo14_addon_payroll_rule_time_parameter-14.0.2.0.2.dist-info/RECORD
